pyrobot/__init__.py
pyrobot/indicators.py
pyrobot/market_data_api.py
pyrobot/portfolio.py
pyrobot/robot.py
pyrobot/trades.py
pyrobot/trading_api.py
trad_robo_python-1.0.6.dist-info/LICENSE.txt
trad_robo_python-1.0.6.dist-info/METADATA
trad_robo_python-1.0.6.dist-info/WHEEL
trad_robo_python-1.0.6.dist-info/top_level.txt
trad_robo_python-1.0.6.dist-info/RECORD
