Metadata-Version: 2.1
Name: trad-robo-python
Version: 1.0.6
Summary: A trading robot written in Python utilizing the Lemon Markets API capable of maintaining a portfolio                of instruments, displaying performance metrics, submitting orders, providing real-time & historical                data and showcasing technical indicators.
Home-page: https://github.com/mh2rashi/Trad-Robo-Python
Author: Hamza Rashid
Author-email: hamza022697@gmail.com
License: UNKNOWN
Keywords: finance,lemon markets,api,trading robot
Platform: UNKNOWN
Classifier: Development Status :: 3 - Alpha
Classifier: Intended Audience :: Developers
Classifier: Intended Audience :: Science/Research
Classifier: Intended Audience :: Financial and Insurance Industry
Classifier: License :: OSI Approved :: MIT License
Classifier: Natural Language :: English
Classifier: Operating System :: OS Independent
Classifier: Programming Language :: Python
Classifier: Programming Language :: Python :: 3
Classifier: Programming Language :: Python :: 3.8
Classifier: Topic :: Database
Classifier: Topic :: Education
Classifier: Topic :: Office/Business
Requires-Python: >=3.8
Requires-Dist: pandas
Requires-Dist: numpy
Requires-Dist: matplotlib
Requires-Dist: requests
